dupychat/__init__.py
dupychat/api.py
dupychat/config/__init__.py
dupychat/config/mylogger.py
dupychat/core/__init__.py
dupychat/core/dupychat.py
dupychat/core_async/__init__.py
dupychat/core_async/buffer.py
dupychat/core_async/livechat.py
dupychat/core_multithread/__init__.py
dupychat/core_multithread/buffer.py
dupychat/core_multithread/livechat.py
dupychat/exceptions.py
dupychat/paramgen/__init__.py
dupychat/paramgen/arcparam.py
dupychat/paramgen/enc.py
dupychat/paramgen/liveparam.py
dupychat/parser/__init__.py
dupychat/parser/live.py
dupychat/processors/__init__.py
dupychat/processors/chat_processor.py
dupychat/processors/combinator.py
dupychat/processors/compatible/__init__.py
dupychat/processors/compatible/processor.py
dupychat/processors/compatible/renderer/__init__.py
dupychat/processors/compatible/renderer/base.py
dupychat/processors/compatible/renderer/currency.py
dupychat/processors/compatible/renderer/legacypaid.py
dupychat/processors/compatible/renderer/membership.py
dupychat/processors/compatible/renderer/paidmessage.py
dupychat/processors/compatible/renderer/paidsticker.py
dupychat/processors/compatible/renderer/textmessage.py
dupychat/processors/default/__init__.py
dupychat/processors/default/custom_encoder.py
dupychat/processors/default/processor.py
dupychat/processors/default/renderer/__init__.py
dupychat/processors/default/renderer/base.py
dupychat/processors/default/renderer/currency.py
dupychat/processors/default/renderer/donation.py
dupychat/processors/default/renderer/legacypaid.py
dupychat/processors/default/renderer/membership.py
dupychat/processors/default/renderer/paidmessage.py
dupychat/processors/default/renderer/paidsticker.py
dupychat/processors/default/renderer/textmessage.py
dupychat/processors/dummy_processor.py
dupychat/processors/html_archiver.py
dupychat/processors/jsonfile_archiver.py
dupychat/processors/simple_display_processor.py
dupychat/processors/speed/__init__.py
dupychat/processors/speed/calculator.py
dupychat-0.1.0.dist-info/LICENSE
dupychat-0.1.0.dist-info/WHEEL
dupychat-0.1.0.dist-info/METADATA
dupychat-0.1.0.dist-info/RECORD
