Metadata-Version: 2.1
Name: dupychat
Version: 0.1.0
Summary: 
Author: dunossauro
Author-email: mendesxeduardo@gmail.com
Requires-Python: >=3.10,<4.0
Classifier: Programming Language :: Python :: 3
Classifier: Programming Language :: Python :: 3.10
Requires-Dist: httpx[http2] (>=0.22.0,<0.23.0)
